radifox/__init__.py
radifox/_static_version.py
radifox/_version.py
radifox/modules/__init__.py
radifox/modules/staging.py
radifox/naming/__init__.py
radifox/naming/imagefile.py
radifox/records/__init__.py
radifox/records/hashing.py
radifox/records/json.py
radifox/records/logging.py
radifox/records/processing.py
radifox/records/qa.py
radifox/records/resize.py
radifox/records/utils.py
radifox-2.1.0.dist-info/LICENSE
radifox-2.1.0.dist-info/METADATA
radifox-2.1.0.dist-info/WHEEL
radifox-2.1.0.dist-info/entry_points.txt
radifox-2.1.0.dist-info/top_level.txt
radifox-2.1.0.dist-info/RECORD
