Metadata-Version: 2.1
Name: radifox
Version: 2.1.0
Summary: Conversion tools using the RADIFOX framework.
Author-email: JH-MIPC <jhmipc@jh.edu>
License: Apache-2.0
Project-URL: Homepage, https://github.com/jh-mipc/radifox
Classifier: Programming Language :: Python :: 3
Classifier: License :: OSI Approved :: Apache Software License
Classifier: Operating System :: OS Independent
Requires-Python: >=3.10
License-File: LICENSE
Requires-Dist: nibabel
Requires-Dist: numpy
Requires-Dist: pillow
Requires-Dist: pyyaml
Requires-Dist: scipy
Requires-Dist: matplotlib
Requires-Dist: trimesh
Requires-Dist: networkx
